[
  {
    "id": "co-ATLAS",
    "raisonSociale": "AtlasCompta SARL",
    "ICE": "001234567890123",
    "IF": "12345678",
    "RC": "CASA-123456",
    "TP": "56789012",
    "devise": "MAD",
    "ville": "Casablanca",
    "tvaPeriode": "mensuel",
    "tvaTaux": [
      20,
      10,
      14,
      7
    ],
    "immobilisations": [
      {
        "id": "IMMO-2022-001",
        "code": "IMMO-LAP",
        "label": "Parc laptops Dell Latitude",
        "category": "Matériel informatique",
        "startDate": "2022-11-01",
        "cost": 240000,
        "residual": 24000,
        "duration": 36
      },
      {
        "id": "IMMO-2023-002",
        "code": "IMMO-SRV",
        "label": "Serveur applicatif Rabat",
        "category": "Infrastructure",
        "startDate": "2023-03-10",
        "cost": 180000,
        "residual": 18000,
        "duration": 48
      },
      {
        "id": "IMMO-2023-003",
        "code": "IMMO-MOB",
        "label": "Mobilier open-space Fès",
        "category": "Aménagement",
        "startDate": "2023-07-01",
        "cost": 95000,
        "residual": 9500,
        "duration": 60
      }
    ]
  }
]
